{
  "users": [
    {
      "id": "1",
      "name": "Myra"
    },
    {
      "id": "2d41",
      "name": "Louise Ruecker"
    },
    {
      "id": "dc42",
      "name": "Mandy Anderson"
    },
    {
      "id": "a949",
      "name": "Phil Crist"
    },
    {
      "id": "c14b",
      "name": "Lila Hirthe DVM"
    },
    {
      "id": "876a",
      "name": "Verna Dooley II"
    },
    {
      "id": "0889",
      "name": "Barbara Dare"
    },
    {
      "id": "6f12",
      "name": "Elvira Adams"
    },
    {
      "id": "4cde",
      "name": "Gloria Cummings"
    },
    {
      "id": "2c3f",
      "name": "Tony D'Amore"
    },
    {
      "id": "ccfe",
      "name": "Mrs. Nicolas Labadie"
    },
    {
      "id": "34fe",
      "name": "Agnes Wilderman"
    },
    {
      "id": "90e1",
      "name": "Francis Kuhic"
    },
    {
      "id": "54b3",
      "name": "Theresa Yost"
    },
    {
      "id": "3ddd",
      "name": "Angel Lockman"
    },
    {
      "id": "2e7d",
      "name": "Joey Kris"
    },
    {
      "id": "3a77",
      "name": "Hubert O'Hara"
    },
    {
      "id": "fe8f",
      "name": "Tabitha West"
    },
    {
      "id": "0c50",
      "name": "Ms. Darla Purdy"
    },
    {
      "id": "312e",
      "name": "Melanie Kuphal"
    },
    {
      "id": "17d0",
      "name": "Alyssa Blick Jr."
    },
    {
      "id": "132b",
      "name": "Miss Clinton Beier"
    },
    {
      "id": "79d0",
      "name": "Raymond Haley"
    },
    {
      "id": "edbb",
      "name": "Paulette Mitchell II"
    },
    {
      "id": "640b",
      "name": "Ms. Victor Hansen"
    },
    {
      "id": "0db5",
      "name": "Stanley O'Reilly"
    },
    {
      "id": "8195",
      "name": "Ms. Janice Hintz"
    },
    {
      "id": "2201",
      "name": "Kelvin Balistreri"
    },
    {
      "id": "0cc9",
      "name": "Gladys Cremin"
    },
    {
      "id": "6548",
      "name": "Lewis Pollich"
    },
    {
      "id": "5d15",
      "name": "Victoria Sipes"
    }
  ],
  "albums": [],
  "photos": []
}